gemini_watermark_remover/__init__.py
gemini_watermark_remover/cli.py
gemini_watermark_remover/watermark_remover.py
gemini_watermark_remover/bg_48.png
gemini_watermark_remover/bg_96.png
py_gemini_watermark_remover-0.2.9.dist-info/METADATA
py_gemini_watermark_remover-0.2.9.dist-info/WHEEL
py_gemini_watermark_remover-0.2.9.dist-info/entry_points.txt
py_gemini_watermark_remover-0.2.9.dist-info/licenses/LICENSE
py_gemini_watermark_remover-0.2.9.dist-info/RECORD
