Metadata-Version: 2.4
Name: py-gemini-watermark-remover
Version: 0.2.9
Summary: Python implementation of a Gemini watermark removal tool using mathematical reverse alpha blending
Project-URL: Homepage, https://github.com/daniel-style/py-gemini-watermark-remover
Project-URL: Repository, https://github.com/daniel-style/py-gemini-watermark-remover
Project-URL: Issues, https://github.com/daniel-style/py-gemini-watermark-remover/issues
Author: py-gemini-watermark-remover contributors
License: MIT
License-File: LICENSE
Keywords: alpha-blending,gemini,image-processing,removal,watermark
Classifier: Development Status :: 4 - Beta
Classifier: Intended Audience :: Developers
Classifier: License :: OSI Approved :: MIT License
Classifier: Programming Language :: Python :: 3
Classifier: Programming Language :: Python :: 3.8
Classifier: Programming Language :: Python :: 3.9
Classifier: Programming Language :: Python :: 3.10
Classifier: Programming Language :: Python :: 3.11
Classifier: Programming Language :: Python :: 3.12
Classifier: Topic :: Multimedia :: Graphics
Requires-Python: >=3.8
Requires-Dist: numpy>=1.24.0
Requires-Dist: opencv-python-headless>=4.8.0
